ring_election/__init__.py
ring_election/core.py
ring_election-0.1.0.dist-info/LICENSE
ring_election-0.1.0.dist-info/METADATA
ring_election-0.1.0.dist-info/WHEEL
ring_election-0.1.0.dist-info/top_level.txt
ring_election-0.1.0.dist-info/RECORD
